advoservice_integration/__init__.py
advoservice_integration/api_client.py
advoservice_integration/configuration.py
advoservice_integration/rest.py
advoservice_integration/api/__init__.py
advoservice_integration/api/default_api.py
advoservice_integration/api/purchase_api.py
advoservice_integration/models/__init__.py
advoservice_integration/models/certificate_purchase_request.py
advoservice_integration/models/certificate_user_details.py
advoservice_integration/models/login_detail.py
advoservice_integration/models/message.py
advoservice_integration/models/package_data.py
advoservice_integration/models/purchase_request.py
advoservice_integration/models/user_details.py
test/__init__.py
test/test_certificate_purchase_request.py
test/test_certificate_user_details.py
test/test_default_api.py
test/test_login_detail.py
test/test_message.py
test/test_package_data.py
test/test_purchase_api.py
test/test_purchase_request.py
test/test_user_details.py
advoservice_integration-1.1.1.dist-info/METADATA
advoservice_integration-1.1.1.dist-info/WHEEL
advoservice_integration-1.1.1.dist-info/top_level.txt
advoservice_integration-1.1.1.dist-info/RECORD
